zwave_me_ws/__init__.py
zwave_me_ws/helpers.py
zwave_me_ws/WebsocketListener.py
zwave_me_ws/ZWaveMe.py
zwave_me_ws-0.4.2.dist-info/METADATA
zwave_me_ws-0.4.2.dist-info/WHEEL
zwave_me_ws-0.4.2.dist-info/RECORD
