Metadata-Version: 2.1
Name: zwave-me-ws
Version: 0.4.2
Summary: Library, implementing websocket connection to ZWave-Me
Home-page: https://github.com/Z-Wave-Me/zwave-me-ws
License: MIT
Author: Dmitry Vlasov
Author-email: kerbalspacema@gmail.com
Requires-Python: >=3.8,<4.0
Classifier: License :: OSI Approved :: MIT License
Classifier: Programming Language :: Python :: 3
Classifier: Programming Language :: Python :: 3.8
Classifier: Programming Language :: Python :: 3.9
Classifier: Programming Language :: Python :: 3.10
Classifier: Programming Language :: Python :: 3.11
Requires-Dist: requests (>=2.28.1,<3.0.0)
Requires-Dist: websocket-client (>=1.2.1,<2.0.0)
Project-URL: Repository, https://github.com/Z-Wave-Me/zwave-me-ws
